pyocse/__init__.py
pyocse/analyze.py
pyocse/build.py
pyocse/convert.py
pyocse/forcefield.py
pyocse/interchange_parmed.py
pyocse/parameters.py
pyocse/pso.py
pyocse/utils.py
pyocse/version.py
pyocse/charmm/__init__.py
pyocse/charmm/structure.py
pyocse/data/ACSALA07.cif
pyocse/data/ACSALA17.cif
pyocse/data/ACSALA23.cif
pyocse/data/BIYRIM01.cif
pyocse/data/WICZUF.cif
pyocse/data/XV_WICZUF_1.toml
pyocse/data/XV_WICZUF_2.toml
pyocse/data/aspirin_gas.toml
pyocse/interfaces/__init__.py
pyocse/interfaces/ambertools.py
pyocse/interfaces/openmm.py
pyocse/interfaces/parmed.py
pyocse/interfaces/rdkit.py
pyocse/lmp/__init__.py
pyocse/lmp/calculator.py
pyocse/lmp/pyxtal_calculator.py
pyocse/lmp/structure.py
pyocse/templates/3pf.in
pyocse/templates/3pf_free.in
pyocse/templates/__init__.py
pyocse/templates/bulk-cycle.in
pyocse/templates/bulk-single.in
pyocse/templates/bulk-tensile.in
pyocse/templates/shear.in
pyocse/templates/slab-3pf.in
pyocse/templates/slab-bend-single.in
pyocse/templates/slab-cycle-CT.in
pyocse/templates/slab-cycle-TC.in
pyocse/templates/tensile.in
pyocse-0.1.3.dist-info/licenses/LICENSE
pyocse-0.1.3.dist-info/METADATA
pyocse-0.1.3.dist-info/WHEEL
pyocse-0.1.3.dist-info/top_level.txt
pyocse-0.1.3.dist-info/RECORD
