Metadata-Version: 2.4
Name: pyocse
Version: 0.1.3
Summary: Python Organic Crystal Simulation Environment
Home-page: https://github.com/MaterSim/pyocse
Author: Qiang Zhu, Shinnosule Hattori
License: MIT
Classifier: Programming Language :: Python :: 3
Classifier: License :: OSI Approved :: MIT License
Classifier: Operating System :: OS Independent
License-File: LICENSE
Requires-Dist: toml
Requires-Dist: xmltodict
Dynamic: author
Dynamic: classifier
Dynamic: description
Dynamic: description-content-type
Dynamic: home-page
Dynamic: license
Dynamic: license-file
Dynamic: requires-dist
Dynamic: summary
